ar/__init__.py
ar/__main__.py
ar/archive.py
ar/substream.py
ar-1.0.0.dist-info/METADATA
ar-1.0.0.dist-info/WHEEL
ar-1.0.0.dist-info/RECORD
