Metadata-Version: 2.3
Name: ar
Version: 1.0.0
Summary: Access ar archive files (.a)!
Project-URL: Repository, https://github.com/vidstige/ar/
Project-URL: Bug Tracker, https://github.com/vidstige/ar/issues
Author-email: Samuel Carlsson <samuel.carlsson@gmail.com>
Keywords: ar,archive,extract,library
Classifier: Development Status :: 4 - Beta
Classifier: Programming Language :: Python
Requires-Python: >=3.7
Provides-Extra: dev
Requires-Dist: mypy; extra == 'dev'
Requires-Dist: pylint; extra == 'dev'
Provides-Extra: test
Requires-Dist: pytest~=7.4.4; extra == 'test'
